molnet/__init__.py
molnet/download.py
molnet/load_functions.py
molnet/molnet_config.py
molnet/splitter.py
molnet/utils.py
molnet_python-0.0.1.dist-info/LICENSE
molnet_python-0.0.1.dist-info/METADATA
molnet_python-0.0.1.dist-info/WHEEL
molnet_python-0.0.1.dist-info/top_level.txt
molnet_python-0.0.1.dist-info/RECORD
