Metadata-Version: 2.1
Name: molnet-python
Version: 0.0.1
Summary: A small package for loading data from MoleculeNet
Home-page: https://github.com/Minys233/molnet-python.git
Author: Minys
Author-email: minys@foxmail.com
License: UNKNOWN
Platform: UNKNOWN
Classifier: Programming Language :: Python :: 3
Classifier: License :: OSI Approved :: MIT License
Classifier: Operating System :: OS Independent
Classifier: Environment :: Console
Requires-Python: >=3.6
Requires-Dist: requests
Requires-Dist: pandas
Requires-Dist: numpy
Requires-Dist: tqdm
Requires-Dist: cloudpickle
